setup.py
cyclone_wtforms/__init__.py
cyclone_wtforms/forms.py
cyclone_wtforms/utils.py
cyclone_wtforms.egg-info/PKG-INFO
cyclone_wtforms.egg-info/SOURCES.txt
cyclone_wtforms.egg-info/dependency_links.txt
cyclone_wtforms.egg-info/requires.txt
cyclone_wtforms.egg-info/top_level.txt