Metadata-Version: 1.0
Name: cyclone-wtforms
Version: 0.1.0
Summary: WTForms for cyclone web server
Home-page: https://github.com/FZambia/cyclone-wtforms
Author: Alexandr Emelin
Author-email: frvzmb@gmail.com
License: http://www.apache.org/licenses/LICENSE-2.0
Keywords: twisted cyclone forms wtforms
Platform: UNKNOWN
